<?xml version="1.0" encoding="UTF-8"?>
<SOAP-ENV:Envelope xmlns:SOAP-ENV="http://schemas.xmlsoap.org/soap/envelope/" xmlns:bibdk="http://oss.dbc.dk/ns/openformatoutput/bibliotekdkdisplay" xmlns:of="http://oss.dbc.dk/ns/openformat"><SOAP-ENV:Body><of:formatResponse><bibdk:fullDisplay><bibdk:work><bibdk:title><bibdk:titleFull>Lov nr. 112 af 13. februar 2012 om tilhold, opholdsforbud og bortvisning</bibdk:titleFull><bibdk:titleSpecific>Lov nr. 112 af 13. februar 2012 om tilhold, opholdsforbud og bortvisning</bibdk:titleSpecific></bibdk:title></bibdk:work><bibdk:adminData><bibdk:pid>870970-basis:29470073</bibdk:pid><bibdk:requestMethod>link</bibdk:requestMethod><bibdk:typeGroup>literature</bibdk:typeGroup><bibdk:typeGroup>online</bibdk:typeGroup></bibdk:adminData><bibdk:main><bibdk:details><bibdk:textLevels><bibdk:textLevel className="link" punctuation=" ; "><bibdk:searchCode word="dkcclterm.nv">04</bibdk:searchCode><bibdk:display>Fagligt niveau</bibdk:display></bibdk:textLevel></bibdk:textLevels><bibdk:descriptionNote>Afsnittene downloades enkeltvis i PDF-format fra: http://jm.schultzboghandel.dk/Navigering/Emnemenu/Hvidb.aspxpublikationsoversigt</bibdk:descriptionNote><bibdk:accessInformation><bibdk:accessUrl>http://jm.schultzboghandel.dk/upload/microsites/jm/ebooks/hvidbog/lov%20nr.%20112%202012%20del%201.pdf</bibdk:accessUrl></bibdk:accessInformation></bibdk:details><bibdk:publicationDetails><bibdk:publisher punctuation=", ">Justitsministeriet, Lovafdelingen</bibdk:publisher><bibdk:publicationYear>2012</bibdk:publicationYear></bibdk:publicationDetails><bibdk:type punctuation=" + ">Ebog</bibdk:type></bibdk:main></bibdk:fullDisplay></of:formatResponse></SOAP-ENV:Body></SOAP-ENV:Envelope>
