<?xml version="1.0" encoding="UTF-8"?>
<SOAP-ENV:Envelope xmlns:SOAP-ENV="http://schemas.xmlsoap.org/soap/envelope/" xmlns:bibdk="http://oss.dbc.dk/ns/openformatoutput/bibliotekdkdisplay" xmlns:of="http://oss.dbc.dk/ns/openformat"><SOAP-ENV:Body><of:formatResponse><bibdk:fullDisplay><bibdk:work><bibdk:title><bibdk:titleFull>Christian Dorph</bibdk:titleFull><bibdk:titleSpecific>Christian Dorph</bibdk:titleSpecific></bibdk:title><bibdk:description><bibdk:subjects><bibdk:subjectHeader>Emne:</bibdk:subjectHeader><bibdk:subject className="link" punctuation=" ; "><bibdk:searchCode phrase="dkcclphrase.lem">Forfatterportrætter</bibdk:searchCode><bibdk:display>Forfatterportrætter</bibdk:display></bibdk:subject></bibdk:subjects></bibdk:description></bibdk:work><bibdk:adminData><bibdk:pid>150005-portraet:45538</bibdk:pid><bibdk:requestMethod>link</bibdk:requestMethod><bibdk:sortKey>A04  A  999  2001  </bibdk:sortKey><bibdk:typeGroup>article</bibdk:typeGroup></bibdk:adminData><bibdk:main><bibdk:details><bibdk:genre>nonfiktion</bibdk:genre><bibdk:genre>forfatterportræt</bibdk:genre><bibdk:references>ISBN: 9788702043242</bibdk:references><bibdk:accessInformation><bibdk:accessUrl>http://www.litteratursiden.dk/?q=node/45538</bibdk:accessUrl></bibdk:accessInformation></bibdk:details><bibdk:publicationDetails><bibdk:publisher punctuation=", ">Litteratursiden</bibdk:publisher><bibdk:publicationYear>1999</bibdk:publicationYear></bibdk:publicationDetails><bibdk:type punctuation=" + ">Artikel</bibdk:type></bibdk:main></bibdk:fullDisplay></of:formatResponse></SOAP-ENV:Body></SOAP-ENV:Envelope>
